rag_finetuning/__init__.py
rag_finetuning/application/__init__.py
rag_finetuning/application/crawlers/__init__.py
rag_finetuning/application/crawlers/base.py
rag_finetuning/application/crawlers/custom_article.py
rag_finetuning/application/crawlers/dispatcher.py
rag_finetuning/application/crawlers/github.py
rag_finetuning/application/crawlers/linkedin.py
rag_finetuning/application/crawlers/medium.py
rag_finetuning/application/dataset/__init__.py
rag_finetuning/application/dataset/constants.py
rag_finetuning/application/dataset/generation.py
rag_finetuning/application/dataset/output_parsers.py
rag_finetuning/application/dataset/utils.py
rag_finetuning/application/networks/__init__.py
rag_finetuning/application/networks/base.py
rag_finetuning/application/networks/embeddings.py
rag_finetuning/application/preprocessing/__init__.py
rag_finetuning/application/preprocessing/chunking_data_handlers.py
rag_finetuning/application/preprocessing/cleaning_data_handlers.py
rag_finetuning/application/preprocessing/dispatchers.py
rag_finetuning/application/preprocessing/embedding_data_handlers.py
rag_finetuning/application/preprocessing/operations/__init__.py
rag_finetuning/application/preprocessing/operations/chunking.py
rag_finetuning/application/preprocessing/operations/cleaning.py
rag_finetuning/application/rag/__init__.py
rag_finetuning/application/rag/base.py
rag_finetuning/application/rag/prompt_templates.py
rag_finetuning/application/rag/query_expanison.py
rag_finetuning/application/rag/reranking.py
rag_finetuning/application/rag/retriever.py
rag_finetuning/application/rag/self_query.py
rag_finetuning/application/utils/__init__.py
rag_finetuning/application/utils/misc.py
rag_finetuning/application/utils/split_user_full_name.py
rag_finetuning/domain/__init__.py
rag_finetuning/domain/base/__init__.py
rag_finetuning/domain/base/nosql.py
rag_finetuning/domain/base/vector.py
rag_finetuning/domain/chunks.py
rag_finetuning/domain/cleaned_documents.py
rag_finetuning-0.1.1.dist-info/LICENSE
rag_finetuning-0.1.1.dist-info/METADATA
rag_finetuning-0.1.1.dist-info/WHEEL
rag_finetuning-0.1.1.dist-info/RECORD
