Metadata-Version: 2.1
Name: RAG_FineTuning
Version: 0.1.1
Summary: RAG Finetuning Project
Author: komalbagwe
Author-email: komalbagwe1997@gmail.com
Requires-Python: >=3.12,<3.13
Classifier: Programming Language :: Python :: 3
Classifier: Programming Language :: Python :: 3.12
Requires-Dist: beautifulsoup4 (>=4.12.3,<5.0.0)
Requires-Dist: chromedriver-autoinstaller (>=0.6.4,<0.7.0)
Requires-Dist: clearml (>=1.10.0,<2.0.0)
Requires-Dist: click (>=8.0.1,<9.0.0)
Requires-Dist: datasets (>=3.0.1,<4.0.0)
Requires-Dist: fake-useragent (>=1.5.1,<2.0.0)
Requires-Dist: fastapi (>=0.100,<=0.110)
Requires-Dist: html2text (>=2024.2.26,<2025.0.0)
Requires-Dist: ipykernel (>=6.29.5,<7.0.0)
Requires-Dist: jinja2 (>=3.1.4,<4.0.0)
Requires-Dist: jmespath (>=1.0.1,<2.0.0)
Requires-Dist: langchain (>=0.2.11,<0.3.0)
Requires-Dist: langchain-community (>=0.2.11,<0.3.0)
Requires-Dist: langchain-openai (>=0.1.3,<0.2.0)
Requires-Dist: loguru (>=0.7.2,<0.8.0)
Requires-Dist: numpy (>=1.26.4,<2.0.0)
Requires-Dist: opik (>=0.2.2,<0.3.0)
Requires-Dist: poethepoet (==0.29.0)
Requires-Dist: pymongo (>=4.6.2,<5.0.0)
Requires-Dist: qdrant-client (>=1.8.0,<2.0.0)
Requires-Dist: requests (>=2.28.0,<3.0.0)
Requires-Dist: rich (>=13.7.1,<14.0.0)
Requires-Dist: selenium (>=4.21.0,<5.0.0)
Requires-Dist: sentence-transformers (>=3.0.0,<4.0.0)
Requires-Dist: tiktoken (>=0.7.0,<0.8.0)
Requires-Dist: uvicorn (>=0.30.6,<0.31.0)
Requires-Dist: webdriver-manager (>=4.0.1,<5.0.0)
